{
  "template": "agency-local-business",
  "templateVersion": "1.0.0",
  "business": {
    "name": "Absolute Comfort HVAC LLC",
    "tagline": "Heating and cooling done right, from Cottonwood to the whole Verde Valley.",
    "category": "HVAC",
    "phone": "(928) 606-1030",
    "email": "absolutecomforthvacllc@gmail.com",
    "address": "1460 E State Route 89A, Suite C",
    "city": "Cottonwood, AZ",
    "domain": "lithacker6458.github.io/demos/absolute-comfort-hvac-llc-classic"
  },
  "brand": {
    "primaryColor": "#0E3A5D",
    "accentColor": "#E25A1B",
    "displayFont": "Fraunces",
    "bodyFont": "Archivo"
  },
  "payments": {
    "provider": "stripe-payment-links",
    "depositUrl": "#",
    "bookUrl": "#",
    "buyUrls": ["#", "#", "#"],
    "notes": "Client-owned Stripe Payment Links ONLY (https://buy.stripe.com/...). Card data flows to Stripe, never to this site or the agency. Empty tokens are stripped in client builds and forced to '#' in demo builds. See docs/STRIPE_SETUP.md."
  },
  "meta": {
    "generatedYear": "2026",
    "brandingSource": "assets/css/custom.css",
    "notes": "All branding (colors, fonts) lives in assets/css/custom.css as CSS custom properties."
  }
}
